{
    "swagger": "2.0",
    "info": {
        "description": "基于 go gin 框架的 API 接口文档",
        "title": "男生自用 API 接口文档",
        "contact": {},
        "version": "1.0"
    },
    "basePath": "/api",
    "paths": {
        "/api/cli/module/create": {
            "get": {
                "description": "get string by ID",
                "consumes": [
                    "application/json"
                ],
                "produces": [
                    "application/json"
                ],
                "tags": [
                    "cli"
                ],
                "summary": "创建模块",
                "parameters": [
                    {
                        "type": "integer",
                        "description": "Account ID",
                        "name": "id",
                        "in": "query",
                        "required": true
                    }
                ],
                "responses": {
                    "200": {
                        "description": "OK",
                        "schema": {
                            "type": "string"
                        }
                    }
                }
            }
        }
    }
}